pst_wrinkle/__init__.py
pst_wrinkle/pst_wrinkle.py
pst_wrinkle-1.4.dist-info/LICENCE
pst_wrinkle-1.4.dist-info/METADATA
pst_wrinkle-1.4.dist-info/WHEEL
pst_wrinkle-1.4.dist-info/top_level.txt
pst_wrinkle-1.4.dist-info/RECORD
