Metadata-Version: 2.1
Name: pst_wrinkle
Version: 1.4
Summary: A small package that wraps selected functions for PST outreach events.
Author-email: Eyyub Unlu <eselimnl@gmail.com>
Project-URL: Homepage, https://github.com/pypa/sampleproject
Project-URL: Issues, https://github.com/pypa/sampleproject/issues
Classifier: Programming Language :: Python :: 3
Classifier: License :: OSI Approved :: MIT License
Classifier: Operating System :: OS Independent
Requires-Python: >=3.8
License-File: LICENCE
